{"cameraMode":{"drawMode":0,"name":"Shaded","section":"Shading Mode"},"sceneLighting":false,"audioPlay":false,"sceneViewState":{"m_AlwaysRefresh":false,"showFog":true,"showSkybox":false,"showFlares":true,"showImageEffects":true,"showParticleSystems":true,"showVisualEffectGraphs":true,"m_FxEnabled":true},"in2DMode":false,"pivot":{"x":960.0,"y":540.0,"z":11.710002899169922},"rotation":{"x":-0.08385010063648224,"y":0.4279664158821106,"z":-0.0399160198867321,"w":-0.8990145921707153},"size":1101.515869140625,"orthographic":false}